power_grid_model_io/__init__.py
power_grid_model_io/py.typed
power_grid_model_io/config/__init__.py
power_grid_model_io/config/examples/__init__.py
power_grid_model_io/config/examples/multipliers.yaml
power_grid_model_io/config/excel/__init__.py
power_grid_model_io/config/excel/vision_en.yaml
power_grid_model_io/config/excel/vision_en_9_7.yaml
power_grid_model_io/config/excel/vision_en_9_8.yaml
power_grid_model_io/config/excel/vision_nl.yaml
power_grid_model_io/converters/__init__.py
power_grid_model_io/converters/base_converter.py
power_grid_model_io/converters/pandapower_converter.py
power_grid_model_io/converters/pgm_json_converter.py
power_grid_model_io/converters/tabular_converter.py
power_grid_model_io/converters/vision_excel_converter.py
power_grid_model_io/data_stores/__init__.py
power_grid_model_io/data_stores/base_data_store.py
power_grid_model_io/data_stores/csv_dir_store.py
power_grid_model_io/data_stores/excel_file_store.py
power_grid_model_io/data_stores/json_file_store.py
power_grid_model_io/data_stores/vision_excel_file_store.py
power_grid_model_io/data_types/__init__.py
power_grid_model_io/data_types/_data_types.py
power_grid_model_io/data_types/tabular_data.py
power_grid_model_io/functions/__init__.py
power_grid_model_io/functions/_functions.py
power_grid_model_io/functions/filters.py
power_grid_model_io/functions/phase_to_phase.py
power_grid_model_io/mappings/__init__.py
power_grid_model_io/mappings/field_mapping.py
power_grid_model_io/mappings/multiplier_mapping.py
power_grid_model_io/mappings/tabular_mapping.py
power_grid_model_io/mappings/unit_mapping.py
power_grid_model_io/mappings/value_mapping.py
power_grid_model_io/utils/__init__.py
power_grid_model_io/utils/auto_id.py
power_grid_model_io/utils/dict.py
power_grid_model_io/utils/download.py
power_grid_model_io/utils/excel_ambiguity_checker.py
power_grid_model_io/utils/json.py
power_grid_model_io/utils/modules.py
power_grid_model_io/utils/parsing.py
power_grid_model_io-1.3.32.dist-info/licenses/LICENSE
power_grid_model_io-1.3.32.dist-info/METADATA
power_grid_model_io-1.3.32.dist-info/WHEEL
power_grid_model_io-1.3.32.dist-info/top_level.txt
power_grid_model_io-1.3.32.dist-info/RECORD
