Metadata-Version: 2.4
Name: power-grid-model-io
Version: 1.3.32
Summary: Power Grid Model Input/Output
Author-email: Contributors to the Power Grid Model project <powergridmodel@lfenergy.org>
License: MPL-2.0
Project-URL: Home-page, https://lfenergy.org/projects/power-grid-model/
Project-URL: GitHub, https://github.com/PowerGridModel/power-grid-model-io
Project-URL: Documentation, https://power-grid-model-io.readthedocs.io/en/stable/
Project-URL: Mailing-list, https://lists.lfenergy.org/g/powergridmodel
Project-URL: Discussion, https://github.com/orgs/PowerGridModel/discussions
Keywords: power grid model,input/output,conversions
Classifier: Programming Language :: Python :: 3
Classifier: Intended Audience :: Developers
Classifier: Intended Audience :: Science/Research
Classifier: License :: OSI Approved :: Mozilla Public License 2.0 (MPL 2.0)
Classifier: Operating System :: Microsoft :: Windows
Classifier: Operating System :: POSIX :: Linux
Classifier: Operating System :: MacOS
Classifier: Topic :: Scientific/Engineering :: Physics
Requires-Python: >=3.11
License-File: LICENSE
Requires-Dist: numpy>=2.0
Requires-Dist: openpyxl
Requires-Dist: packaging>=25.0
Requires-Dist: pandas
Requires-Dist: power_grid_model>=1.8
Requires-Dist: pyyaml
Requires-Dist: structlog
Requires-Dist: tqdm
Provides-Extra: dev
Requires-Dist: pre-commit; extra == "dev"
Requires-Dist: pylint; extra == "dev"
Requires-Dist: pytest; extra == "dev"
Requires-Dist: pytest-cov; extra == "dev"
Requires-Dist: ruff; extra == "dev"
Requires-Dist: pydantic>2; extra == "dev"
Requires-Dist: pandapower>2.11.1; extra == "dev"
Requires-Dist: lxml; extra == "dev"
Provides-Extra: examples
Requires-Dist: power-grid-model>1.9.80; extra == "examples"
Requires-Dist: pandapower>2.11.1; extra == "examples"
Requires-Dist: pyarrow; extra == "examples"
Provides-Extra: doc
Requires-Dist: sphinx; extra == "doc"
Requires-Dist: myst-nb; extra == "doc"
Requires-Dist: sphinx_rtd_theme; extra == "doc"
Requires-Dist: readthedocs-sphinx-search; extra == "doc"
Requires-Dist: sphinx-hoverxref; extra == "doc"
Requires-Dist: numpydoc; extra == "doc"
Dynamic: license-file
